{
    "topic": "lecture materials and Moodle",
    "study_program": "bachelor-wirtschaftsinformatik",
    "correspondence": [
        {
            "orderKey": 0,
            "sender": "STUDENT",
            "message": "I am starting my studies in business informatics this year and would like to find out whether the lecture notes are uploaded to Moodle or whether they are available or can be purchased elsewhere.\""
        },
        {
            "orderKey": 1,
            "sender": "AA",
            "message": "The professors will tell you where the materials are available in the first lecture. Be sure to go to every first lecture and check the Moodle courses to see if there is any information about it."
        }
    ]
}