{
    "topic": "Fristverlängerung im Studium",
    "correspondence": [
        {
            "orderKey": 0,
            "sender": "STUDENT",
            "message": "Sehr geehrte Frau <ANONYMIZED>, ich möchte erneut um eine Fristverlängerung bitten. Leider hat meine Armverletzung im letzten Sommersemester zu weitreichenden Konsequenzen geführt und meine Effizienz im Studium stark beeinträchtigt. Obwohl mir im letzten Jahr mitgeteilt wurde, dass ich keine Verlängerung benötige, sehe ich weiterhin Bedarf aufgrund der anhaltenden Einschränkungen. Ich wäre Ihnen dankbar, wenn Sie meinen Antrag erneut prüfen könnten. Alle relevanten Unterlagen und Attest, die diesen Antrag unterstützen, habe ich beigefügt. Vielen Dank für Ihr Verständnis. Mit freundlichen Grüßen, <ANONYMIZED>\""
        },
        {
            "orderKey": 1,
            "sender": "AA",
            "message": "<ANONYMIZED>, wenn ich es richtig sehe, dann ist das aktuelle Sommersemester Ihr 6. Fachsemester. Da Sie Ihr Studium im WS 21/22 begonnen haben, profitieren Sie von einer pauschalen Fristverlängerung, d.h. Sie müssen am Ende dieses Semesters die Studienfortschrittskontrolle des 5. Semesters erreichen, also 90 ECTS. Laut Ihrem Kontoauszug haben Sie aktuell bereits 100 ECTS, Sie sind also noch in der Frist und können keinen Antrag auf Fristverlängerung stellen. Dies ist erst zu dem Zeitpunkt möglich, zu dem Sie die Credithürde nicht überwinden. Es sieht so aus, als hätten Sie dieses Semester nicht viele Prüfungen bestanden. Planen Sie an den Wiederholungsprüfungen teilzunehmen? Vielleicht ist es sinnvoll, in eine unserer Sprechstunden zu kommen, damit wir in Ruhe besprechen können, woran es liegt, dass es gerade nicht so gut läuft und wie es im kommenden Semester besser laufen könnte. Viele Grüße, <ANONYMIZED>."
        }
    ]
}