{
    "topic": "Betreff: Fehlende ECTS und Unterstützung bei der Masterarbeit",
    "correspondence": [
        {
            "orderKey": 0,
            "sender": "STUDENT",
            "message": "Sehr geehrte Informatik Studienberatung,\n\nMir ist am Wochenende ein Problem bewusst geworden. Und zwar handelt es sich um folgende Situation:\n\nIch hatte geplant im SS2024 meine Masterarbeit zu schreiben und dann im kommenden Semester plangemäß mein Studium abzuschließen. Nun hatte ich viele Schwierigkeiten mit der Suche nach einem geeigneten Betreuer für mein Wunschthema, was schließlich dazu geführt hat, dass ich mich für ein anderes Thema entschieden habe. Meine Bewerbungen auf andere Themen wurden aber lange nicht beantwortet oder ich habe Absagen bekommen. Ich habe nun aber endlich ein Thema.\n\nAllerdings fehlen mir durch diese lange Verzögerung nun 6 ECTS. Diese würde ich im WS24/25 neben meiner Masterarbeit machen, um mein Studium abschließen zu können. Um ehrlich zu sein, dachte ich auch ursprünglich, wegen der Corona-Semester noch ein Semester mehr Zeit zu haben...\n\nGibt es eine Lösung für diese fehlenden ECTS? Zum Beispiel eine nachträgliche Eintragung eines Urlaubssemesters oder ähnliches. Ist es diesbezüglich angebracht, vielleicht einmal persönlich vorbeizukommen?\n\nVielen Dank und freundliche Grüße.\""
        },
        {
            "orderKey": 1,
            "sender": "AA",
            "message": "Das klingt ja nicht so gut. Bitte schicken Sie mir Ihren aktuellen TUMonline Kontoauszug und die Studienverlaufsbescheinigung, damit ich mir ein Bild Ihrer Lage machen kann. Ist Ihre Masterarbeit denn schon angemeldet? Viele Grüße."
        }
    ]
}